{"name":"Raptget","tagline":"A gem providing a ruby interface to the apt-get package manager.","body":"README for raptget\r\n==================\r\n\r\nRaptget is a gem providing a ruby interface to the apt-get package manager.\r\n\r\nTo install, type 'gem install raptget'\r\n\r\nUsage:\r\n\r\n```ruby\r\n  require 'raptget'\r\n  include Raptget\r\n\r\n  packages = Array.new\r\n  packages.push('iagno')\r\n  packages.push('gnome-games')\r\n\r\n  aptget = Aptget.new\r\n  aptget.install(packages)\r\n```\r\n","google":"","note":"Don't delete this file! It's used internally to help with page regeneration."}